hydrotools/_restclient/__init__.py
hydrotools/_restclient/_async_helpers.py
hydrotools/_restclient/_iterable_nonstring.py
hydrotools/_restclient/_restclient.py
hydrotools/_restclient/_restclient_sigs.py
hydrotools/_restclient/_version.py
hydrotools/_restclient/async_client.py
hydrotools/_restclient/urllib.py
hydrotools/_restclient/urllib_types.py
hydrotools/_restclient/utilities.py
hydrotools_restclient-4.1.0.dist-info/licenses/LICENSE
hydrotools_restclient-4.1.0.dist-info/licenses/NOTICE
hydrotools_restclient-4.1.0.dist-info/METADATA
hydrotools_restclient-4.1.0.dist-info/WHEEL
hydrotools_restclient-4.1.0.dist-info/top_level.txt
hydrotools_restclient-4.1.0.dist-info/RECORD
