Metadata-Version: 2.4
Name: hydrotools._restclient
Version: 4.1.0
Summary: General REST api client with built in request caching and retries.
Author-email: Austin Raney <aaraney@protonmail.com>
License: 
Project-URL: Homepage, https://github.com/NOAA-OWP/hydrotools
Project-URL: Documentation, https://noaa-owp.github.io/hydrotools/hydrotools._restclient.html
Project-URL: Repository, https://github.com/NOAA-OWP/hydrotools/tree/main/python/_restclient
Project-URL: Bug Tracker, https://github.com/NOAA-OWP/hydrotools/issues
Classifier: Development Status :: 5 - Production/Stable
Classifier: Intended Audience :: Education
Classifier: Intended Audience :: Science/Research
Classifier: License :: OSI Approved :: Apache Software License
Classifier: Programming Language :: Python :: 3.9
Classifier: Programming Language :: Python :: 3.10
Classifier: Programming Language :: Python :: 3.11
Classifier: Programming Language :: Python :: 3.12
Classifier: Topic :: Scientific/Engineering :: Hydrology
Classifier: Operating System :: OS Independent
Requires-Python: >=3.9
License-File: LICENSE
License-File: NOTICE
Requires-Dist: aiohttp
Requires-Dist: aiohttp_client_cache[sqlite]>=0.9.0
Requires-Dist: python-forge
Requires-Dist: aiosqlite
Requires-Dist: pandas
Provides-Extra: develop
Requires-Dist: pytest; extra == "develop"
Requires-Dist: pytest-aiohttp; extra == "develop"
Dynamic: license-file
